gestao_imc/__init__.py
gestao_imc/gestão_de_imc.py
gestao_imc-0.1.5.dist-info/METADATA
gestao_imc-0.1.5.dist-info/WHEEL
gestao_imc-0.1.5.dist-info/top_level.txt
gestao_imc-0.1.5.dist-info/RECORD
